phylotypes/__init__.py
phylotypes/add_phylotypes.py
phylotypes/phylotypes.py
phylotypes-1.0.0.dist-info/LICENSE
phylotypes-1.0.0.dist-info/METADATA
phylotypes-1.0.0.dist-info/WHEEL
phylotypes-1.0.0.dist-info/entry_points.txt
phylotypes-1.0.0.dist-info/top_level.txt
phylotypes-1.0.0.dist-info/RECORD
