Metadata-Version: 2.1
Name: phylotypes
Version: 1.0.0
Summary: Group phylogenetically placed sequence variants into phylotypes
Home-page: https://github.com/jgolob/phylotypes
Author: Jonathan Louis Golob
Author-email: j-dev@golob.org
Project-URL: Bug Tracker, https://github.com/jgolob/phylotypes/issues
Classifier: Programming Language :: Python :: 3
Classifier: License :: OSI Approved :: MIT License
Classifier: Operating System :: OS Independent
Requires-Python: >=3.6
License-File: LICENSE
Requires-Dist: biopython
Requires-Dist: scikit-bio
Requires-Dist: numpy
Requires-Dist: scikit-learn >=1.3.0
Requires-Dist: taichi
